tvdb_v4_official.py
tvdb_v4_official-1.1.0.dist-info/METADATA
tvdb_v4_official-1.1.0.dist-info/WHEEL
tvdb_v4_official-1.1.0.dist-info/top_level.txt
tvdb_v4_official-1.1.0.dist-info/RECORD
