Metadata-Version: 2.1
Name: tvdb-v4-official
Version: 1.1.0
Summary: tvdb-api-v4 utility package
Home-page: https://github.com/thetvdb/tvdb-v4-python
Author: Weylin Wagnon
Author-email: <support@thetvdb.com>
Keywords: python,tvdb
Classifier: Development Status :: 3 - Alpha
Classifier: Intended Audience :: Developers
Classifier: Programming Language :: Python :: 3
Classifier: Operating System :: MacOS :: MacOS X
Classifier: Operating System :: Microsoft :: Windows
